my_own_library/__init__.py
my_own_library/calculator.py
my_own_library-0.1.0.dist-info/licenses/LICENSE
my_own_library-0.1.0.dist-info/METADATA
my_own_library-0.1.0.dist-info/WHEEL
my_own_library-0.1.0.dist-info/top_level.txt
my_own_library-0.1.0.dist-info/RECORD
